{
  "description": "Per-TLD bootstrap data, from IANA sources",
  "publication": "2026-05-25T17:27:52Z",
  "sources": {
    "iana_root_db": "https://www.iana.org/domains/root/db",
    "iana_rdap": "https://data.iana.org/rdap/dns.json"
  },
  "tld": {
    "tld": "helsinki",
    "delegated": true,
    "iana_tag": "generic",
    "type": "gtld",
    "orgs": {
      "iana": {
        "sponsor": "City of Helsinki",
        "admin": "Digitalization Unit, City of Helsinki",
        "tech": "Identity Digital Limited"
      },
      "icann": {
        "registry_operator": "City of Helsinki",
        "specification_13": false,
        "third_or_lower_level_registration": false,
        "application_id": "1-1865-66478",
        "registry_operator_country_code": null,
        "date_contract_signed": "2015-02-05",
        "date_delegated": "2016-01-26",
        "contract_terminated": false,
        "date_removed": null
      }
    },
    "nameservers": [
      {
        "hostname": "a0.nic.helsinki",
        "ipv4": [
          {
            "ip": "65.22.220.33",
            "asn": 12041,
            "as_org": "AS-AFILIAS1",
            "as_country": "US"
          }
        ],
        "ipv6": [
          {
            "ip": "2a01:8840:d6::33",
            "asn": 12041,
            "as_org": "AS-AFILIAS1",
            "as_country": "US"
          }
        ]
      },
      {
        "hostname": "a2.nic.helsinki",
        "ipv4": [
          {
            "ip": "65.22.223.33",
            "asn": 207266,
            "as_org": "AFILIAS-SECONDARY-DNS",
            "as_country": "IE"
          }
        ],
        "ipv6": [
          {
            "ip": "2a01:8840:d9::33",
            "asn": 207266,
            "as_org": "AFILIAS-SECONDARY-DNS",
            "as_country": "IE"
          }
        ]
      },
      {
        "hostname": "b0.nic.helsinki",
        "ipv4": [
          {
            "ip": "65.22.221.33",
            "asn": 12041,
            "as_org": "AS-AFILIAS1",
            "as_country": "US"
          }
        ],
        "ipv6": [
          {
            "ip": "2a01:8840:d7::33",
            "asn": 12041,
            "as_org": "AS-AFILIAS1",
            "as_country": "US"
          }
        ]
      },
      {
        "hostname": "c0.nic.helsinki",
        "ipv4": [
          {
            "ip": "65.22.222.33",
            "asn": 12041,
            "as_org": "AS-AFILIAS1",
            "as_country": "US"
          }
        ],
        "ipv6": [
          {
            "ip": "2a01:8840:d8::33",
            "asn": 12041,
            "as_org": "AS-AFILIAS1",
            "as_country": "US"
          }
        ]
      }
    ],
    "registry_url": "http://www.hel.fi",
    "whois_server": "whois.nic.helsinki",
    "rdap_server": "https://rdap.identitydigital.services/rdap/",
    "tld_created": "2015-12-10",
    "tld_updated": [
      "2025-08-27"
    ],
    "annotations": {
      "iana_tech_alias": "Identity Digital",
      "iana_tech_slug": "identity-digital",
      "rdap_source": "IANA",
      "registry_agreement_types": [
        "base",
        "non_sponsored"
      ],
      "as_org_aliases": [
        "Identity Digital"
      ],
      "as_org_slugs": [
        "identity-digital"
      ],
      "geographic_scope": "city"
    }
  }
}
