{
  "description": "Per-TLD bootstrap data, from IANA sources",
  "publication": "2026-05-24T22:45:17Z",
  "sources": {
    "iana_root_db": "https://www.iana.org/domains/root/db",
    "iana_rdap": "https://data.iana.org/rdap/dns.json"
  },
  "tld": {
    "tld": "sr",
    "delegated": true,
    "iana_tag": "country-code",
    "type": "cctld",
    "orgs": {
      "tld_manager": "Telesur",
      "admin": "Telesur",
      "tech": "Telesur",
      "iana": {
        "sponsor": "Telesur",
        "admin": "Telesur",
        "tech": "Telesur"
      }
    },
    "nameservers": [
      {
        "hostname": "ns1.nic.sr",
        "ipv4": [
          {
            "ip": "168.195.219.210",
            "asn": 263799,
            "as_org": "CARIBBEAN COMMUNICATION SERVICES",
            "as_country": "SR"
          }
        ],
        "ipv6": [
          {
            "ip": "2803:ff40:a251:0:168:195:219:2",
            "asn": 263799,
            "as_org": "CARIBBEAN COMMUNICATION SERVICES",
            "as_country": "SR"
          }
        ]
      },
      {
        "hostname": "ns2.nic.sr",
        "ipv4": [
          {
            "ip": "168.195.216.214",
            "asn": 27775,
            "as_org": "Telecommunicationcompany Suriname - TeleSur",
            "as_country": "SR"
          }
        ],
        "ipv6": [
          {
            "ip": "2803:ff40:a000:2501:168:195:216:2",
            "asn": 263799,
            "as_org": "CARIBBEAN COMMUNICATION SERVICES",
            "as_country": "SR"
          }
        ]
      },
      {
        "hostname": "ns3.nic.sr",
        "ipv4": [
          {
            "ip": "45.83.205.134",
            "asn": 211588,
            "as_org": "XYPHEN",
            "as_country": "NL"
          }
        ],
        "ipv6": [
          {
            "ip": "2a0f:ff40:100:3112:2d53:cd87::",
            "asn": 0,
            "as_org": "Not routed",
            "as_country": "None"
          }
        ]
      }
    ],
    "registry_url": "https://isp.datasur.sr/",
    "whois_server": "whois.sr",
    "rdap_server": "https://whois.sr/rdap/",
    "tld_created": "1991-09-03",
    "tld_updated": [
      "2026-04-17"
    ],
    "annotations": {
      "rdap_source": "IANA",
      "country_name_iso": "Suriname",
      "geographic_scope": "country"
    }
  }
}
